{"id":"998964066700582080","name":"Grocery Shopping app","lastUpdateDate":"2021-07-19T14:46:33.472Z","publisherHandle":"uisoup","publisherImage":"https://www.gravatar.com/avatar/6847f041ea9a77da5eef6645b1ba2b20?size=240&default=https%3A%2F%2Fs3-alpha.figma.com%2Fstatic%2Fuser_u_v2.png","publisherId":"926057881825288010","publisherName":"UISOUP","thumbnailUrl":"https://s3-alpha.figma.com/hub/file/990058899/653a157c-c25d-4150-89ed-3a98a7086640-cover.png","description":"<p>Grocery Shopping app downloads free. More free interesting resources on our website: <a href=\"http://uisoup.com/\" rel=\"noreferrer noopener nofollow\" target=\"_blank\">http://uisoup.com/</a></p>","url":"https://www.figma.com/community/file/998964066700582080"}
