{"id":"1113063400736494776","name":"Vipin Kumar","lastUpdateDate":"2022-05-30T11:16:34.629Z","publisherHandle":"vipinku","publisherImage":"https://www.gravatar.com/avatar/532563bf08ac48e59d283402b44ba6f0?size=240&default=https%3A%2F%2Fs3-alpha.figma.com%2Fstatic%2Fuser_v_v2.png","publisherId":"1113047258410182366","publisherName":"Vipin Kumar","thumbnailUrl":"https://s3-alpha.figma.com/hub/file/1927304524/df7eecc4-2485-4838-bb6b-138d6f2bdab8-cover.png","description":"<p>Node.Js , mongoDb  ,Express Api for product </p>","url":"https://www.figma.com/community/file/1113063400736494776"}
