{"id":"1113119587208925444","name":"Leis da Gestalt - Equipe Terror do SMD - 2022","lastUpdateDate":"2022-05-30T14:59:50.469Z","publisherHandle":"terrorSMD","publisherImage":"https://www.gravatar.com/avatar/d3512d69beb352f5e471b8d8859f3f61?size=240&default=https%3A%2F%2Fs3-alpha.figma.com%2Fstatic%2Fuser_m_v2.png","publisherId":"1102044504153799185","publisherName":"Manoel Costa","thumbnailUrl":"https://s3-alpha.figma.com/hub/file/1927418700/cedce254-13e7-4589-ad0f-45c6ef9679d0-cover.png","description":"","url":"https://www.figma.com/community/file/1113119587208925444"}
