[{"date":"2021-10-16","duplicateCount":1121,"likeCount":15,"viewCount":59012,"commentCount":0,"version":"6"},{"date":"2021-10-17","duplicateCount":1122,"likeCount":15,"viewCount":59017,"commentCount":0,"version":"6"},{"date":"2021-10-18","duplicateCount":1126,"likeCount":15,"viewCount":59033,"commentCount":0,"version":"6"},{"date":"2021-10-19","duplicateCount":1130,"likeCount":15,"viewCount":59051,"commentCount":0,"version":"6"},{"date":"2021-10-20","duplicateCount":1142,"likeCount":15,"viewCount":59075,"commentCount":0,"version":"6"},{"date":"2021-10-21","duplicateCount":1144,"likeCount":15,"viewCount":59102,"commentCount":0,"version":"6"}]
