[{"date":"2021-10-16","duplicateCount":0,"likeCount":1,"viewCount":2,"commentCount":0,"version":"1"},{"date":"2021-10-17","duplicateCount":1,"likeCount":1,"viewCount":3,"commentCount":0,"version":"1"},{"date":"2021-10-18","duplicateCount":4,"likeCount":1,"viewCount":12,"commentCount":0,"version":"1"},{"date":"2021-10-19","duplicateCount":7,"likeCount":1,"viewCount":19,"commentCount":0,"version":"1"},{"date":"2021-10-20","duplicateCount":8,"likeCount":1,"viewCount":24,"commentCount":0,"version":"1"},{"date":"2021-10-21","duplicateCount":15,"likeCount":1,"viewCount":36,"commentCount":0,"version":"1"},{"date":"2021-10-22","duplicateCount":18,"likeCount":1,"viewCount":46,"commentCount":0,"version":"1"},{"date":"2021-10-23","duplicateCount":22,"likeCount":1,"viewCount":57,"commentCount":0,"version":"1"},{"date":"2021-10-24","duplicateCount":25,"likeCount":1,"viewCount":63,"commentCount":0,"version":"1"},{"date":"2021-10-25","duplicateCount":26,"likeCount":1,"viewCount":72,"commentCount":0,"version":"1"},{"date":"2021-10-26","duplicateCount":26,"likeCount":1,"viewCount":75,"commentCount":0,"version":"1"},{"date":"2021-10-27","duplicateCount":32,"likeCount":1,"viewCount":87,"commentCount":0,"version":"1"},{"date":"2021-10-28","duplicateCount":34,"likeCount":1,"viewCount":101,"commentCount":0,"version":"1"},{"date":"2021-10-29","duplicateCount":35,"likeCount":1,"viewCount":106,"commentCount":0,"version":"1"},{"date":"2021-10-30","duplicateCount":37,"likeCount":1,"viewCount":111,"commentCount":0,"version":"1"},{"date":"2021-10-31","duplicateCount":38,"likeCount":1,"viewCount":116,"commentCount":0,"version":"1"},{"date":"2021-11-01","duplicateCount":39,"likeCount":1,"viewCount":118,"commentCount":0,"version":"1"},{"date":"2021-11-02","duplicateCount":42,"likeCount":1,"viewCount":125,"commentCount":0,"version":"1"},{"date":"2021-11-03","duplicateCount":43,"likeCount":1,"viewCount":129,"commentCount":0,"version":"1"},{"date":"2021-11-04","duplicateCount":45,"likeCount":1,"viewCount":132,"commentCount":0,"version":"1"},{"date":"2021-11-05","duplicateCount":45,"likeCount":1,"viewCount":135,"commentCount":0,"version":"1"},{"date":"2021-11-06","duplicateCount":49,"likeCount":1,"viewCount":142,"commentCount":0,"version":"1"},{"date":"2021-11-07","duplicateCount":49,"likeCount":1,"viewCount":145,"commentCount":0,"version":"1"},{"date":"2021-11-08","duplicateCount":49,"likeCount":1,"viewCount":150,"commentCount":0,"version":"1"},{"date":"2021-11-09","duplicateCount":50,"likeCount":1,"viewCount":156,"commentCount":0,"version":"1"},{"date":"2021-11-10","duplicateCount":51,"likeCount":1,"viewCount":164,"commentCount":0,"version":"1"}]
