{"id":"1012724537100332251","name":"MG3","lastUpdateDate":"2021-08-26T14:30:28.567Z","publisherHandle":"gabrielkenzo07","publisherImage":"https://www.gravatar.com/avatar/93f1ddfcd8b19896b069bf8a1eda0286?size=240&default=https%3A%2F%2Fs3-alpha.figma.com%2Fstatic%2Fuser_g_v2.png","publisherId":"1012695583235117469","publisherName":"Gabriel Kenzo Ito Takahashi","thumbnailUrl":"https://s3-alpha.figma.com/hub/file/1082115549/3a43a429-4d61-4d45-8ec5-5c73230f8401-cover.png","description":"","url":"https://www.figma.com/community/file/1012724537100332251"}
