{"id":"969941235839543745","name":"SMART速 Health Card Reference Designs","lastUpdateDate":"2021-05-06T14:05:39.877Z","publisherHandle":"erinfuller","publisherImage":"https://www.gravatar.com/avatar/c3689838108645d742d5b3aa4f119ff7?size=240&default=https%3A%2F%2Fs3-alpha.figma.com%2Fstatic%2Fuser_e_v2.png","publisherId":"920338993869230954","publisherName":"Erin Fuller","thumbnailUrl":"https://s3-alpha.figma.com/hub/file/833438753/0c944689-35c9-44f0-9e80-27ad9447b815-cover.png","description":"<p>This work provides SMART速 Health Cards (https://smarthealth.cards/) and the implementers with (1) guidance on appropriate display and use of SMART速 Health Cards and (2) reference designs.</p><p><br></p><p>The overall objective is to encourage consistent visual representations of SMART Health Cards to increase recognition among users and verifiers.</p><p><br></p><p>Note that these reference designs refer to the VCI SMART速 Health Cards: Vaccination &amp; Testing Implementation Guide (https://vci.org/ig/vaccination-and-testing/)</p><p><br></p><p>Open source at: https://github.com/smart-on-fhir/health-cards-designs</p>","url":"https://www.figma.com/community/file/969941235839543745"}
