[{"date":"2021-10-16","duplicateCount":1101,"likeCount":23,"viewCount":40688,"commentCount":0,"version":"1"},{"date":"2021-10-17","duplicateCount":1101,"likeCount":23,"viewCount":40689,"commentCount":0,"version":"1"},{"date":"2021-10-18","duplicateCount":1103,"likeCount":23,"viewCount":40694,"commentCount":0,"version":"1"},{"date":"2021-10-19","duplicateCount":1103,"likeCount":23,"viewCount":40701,"commentCount":0,"version":"1"},{"date":"2021-10-20","duplicateCount":1106,"likeCount":23,"viewCount":40708,"commentCount":0,"version":"1"},{"date":"2021-10-21","duplicateCount":1107,"likeCount":23,"viewCount":40712,"commentCount":0,"version":"1"},{"date":"2021-10-22","duplicateCount":1114,"likeCount":23,"viewCount":40723,"commentCount":0,"version":"1"},{"date":"2021-10-23","duplicateCount":1116,"likeCount":23,"viewCount":40731,"commentCount":0,"version":"1"},{"date":"2021-10-24","duplicateCount":1117,"likeCount":23,"viewCount":40733,"commentCount":0,"version":"1"},{"date":"2021-10-25","duplicateCount":1121,"likeCount":23,"viewCount":40737,"commentCount":0,"version":"1"},{"date":"2021-10-26","duplicateCount":1123,"likeCount":23,"viewCount":40740,"commentCount":0,"version":"1"},{"date":"2021-10-27","duplicateCount":1126,"likeCount":23,"viewCount":40749,"commentCount":0,"version":"1"},{"date":"2021-10-28","duplicateCount":1129,"likeCount":23,"viewCount":40756,"commentCount":0,"version":"1"},{"date":"2021-10-29","duplicateCount":1131,"likeCount":23,"viewCount":40760,"commentCount":0,"version":"1"},{"date":"2021-10-30","duplicateCount":1133,"likeCount":23,"viewCount":40763,"commentCount":0,"version":"1"}]
