[{"date":"2021-10-16","duplicateCount":579,"likeCount":14,"viewCount":36693,"commentCount":2,"version":"1"},{"date":"2021-10-17","duplicateCount":580,"likeCount":14,"viewCount":36696,"commentCount":2,"version":"1"},{"date":"2021-10-18","duplicateCount":580,"likeCount":14,"viewCount":36700,"commentCount":2,"version":"1"},{"date":"2021-10-19","duplicateCount":581,"likeCount":14,"viewCount":36702,"commentCount":2,"version":"1"},{"date":"2021-10-20","duplicateCount":581,"likeCount":14,"viewCount":36702,"commentCount":2,"version":"1"},{"date":"2021-10-21","duplicateCount":582,"likeCount":14,"viewCount":36706,"commentCount":2,"version":"1"},{"date":"2021-10-22","duplicateCount":582,"likeCount":14,"viewCount":36710,"commentCount":2,"version":"1"},{"date":"2021-10-23","duplicateCount":582,"likeCount":14,"viewCount":36712,"commentCount":2,"version":"1"},{"date":"2021-10-24","duplicateCount":584,"likeCount":14,"viewCount":36714,"commentCount":2,"version":"1"},{"date":"2021-10-25","duplicateCount":584,"likeCount":14,"viewCount":36714,"commentCount":2,"version":"1"},{"date":"2021-10-26","duplicateCount":585,"likeCount":14,"viewCount":36717,"commentCount":2,"version":"1"},{"date":"2021-10-27","duplicateCount":586,"likeCount":14,"viewCount":36718,"commentCount":2,"version":"1"},{"date":"2021-10-28","duplicateCount":586,"likeCount":14,"viewCount":36719,"commentCount":2,"version":"1"},{"date":"2021-10-29","duplicateCount":587,"likeCount":14,"viewCount":36720,"commentCount":2,"version":"1"},{"date":"2021-10-30","duplicateCount":587,"likeCount":14,"viewCount":36720,"commentCount":2,"version":"1"},{"date":"2021-10-31","duplicateCount":587,"likeCount":14,"viewCount":36721,"commentCount":2,"version":"1"},{"date":"2021-11-01","duplicateCount":587,"likeCount":15,"viewCount":36722,"commentCount":2,"version":"1"},{"date":"2021-11-02","duplicateCount":587,"likeCount":15,"viewCount":36722,"commentCount":2,"version":"1"},{"date":"2021-11-03","duplicateCount":587,"likeCount":15,"viewCount":36724,"commentCount":2,"version":"1"},{"date":"2021-11-04","duplicateCount":587,"likeCount":15,"viewCount":36726,"commentCount":2,"version":"1"},{"date":"2021-11-05","duplicateCount":588,"likeCount":15,"viewCount":36727,"commentCount":2,"version":"1"},{"date":"2021-11-06","duplicateCount":590,"likeCount":15,"viewCount":36730,"commentCount":2,"version":"1"},{"date":"2021-11-07","duplicateCount":590,"likeCount":15,"viewCount":36731,"commentCount":2,"version":"1"},{"date":"2021-11-08","duplicateCount":591,"likeCount":15,"viewCount":36732,"commentCount":2,"version":"1"},{"date":"2021-11-09","duplicateCount":592,"likeCount":15,"viewCount":36735,"commentCount":2,"version":"1"},{"date":"2021-11-10","duplicateCount":592,"likeCount":15,"viewCount":36737,"commentCount":2,"version":"1"},{"date":"2021-11-11","duplicateCount":592,"likeCount":15,"viewCount":36739,"commentCount":2,"version":"1"},{"date":"2021-11-12","duplicateCount":592,"likeCount":15,"viewCount":36741,"commentCount":2,"version":"1"},{"date":"2021-11-13","duplicateCount":592,"likeCount":15,"viewCount":1561,"commentCount":2,"version":"1"},{"date":"2021-11-14","duplicateCount":593,"likeCount":15,"viewCount":1562,"commentCount":2,"version":"1"},{"date":"2021-11-15","duplicateCount":594,"likeCount":15,"viewCount":1565,"commentCount":2,"version":"1"},{"date":"2021-11-16","duplicateCount":595,"likeCount":15,"viewCount":1567,"commentCount":2,"version":"1"},{"date":"2021-11-17","duplicateCount":597,"likeCount":15,"viewCount":1572,"commentCount":3,"version":"1"},{"date":"2021-11-18","duplicateCount":599,"likeCount":15,"viewCount":1576,"commentCount":3,"version":"1"},{"date":"2021-11-19","duplicateCount":599,"likeCount":15,"viewCount":1578,"commentCount":3,"version":"1"},{"date":"2021-11-20","duplicateCount":600,"likeCount":16,"viewCount":1579,"commentCount":3,"version":"1"},{"date":"2021-11-21","duplicateCount":604,"likeCount":16,"viewCount":1586,"commentCount":3,"version":"1"},{"date":"2021-11-22","duplicateCount":604,"likeCount":16,"viewCount":1586,"commentCount":3,"version":"1"},{"date":"2021-11-23","duplicateCount":604,"likeCount":16,"viewCount":1590,"commentCount":3,"version":"1"},{"date":"2021-11-24","duplicateCount":605,"likeCount":16,"commentCount":3,"version":"1"},{"date":"2021-11-25","duplicateCount":605,"likeCount":16,"commentCount":3,"version":"1"},{"date":"2021-11-26","duplicateCount":606,"likeCount":16,"commentCount":3,"version":"1"},{"date":"2021-11-27","duplicateCount":606,"likeCount":16,"commentCount":3,"version":"1"},{"date":"2021-11-28","duplicateCount":606,"likeCount":16,"commentCount":3,"version":"1"},{"date":"2021-11-29","duplicateCount":606,"likeCount":16,"commentCount":3,"version":"1"},{"date":"2021-11-30","duplicateCount":607,"likeCount":16,"commentCount":3,"version":"1"},{"date":"2021-12-01","duplicateCount":607,"likeCount":16,"commentCount":3,"version":"1"},{"date":"2021-12-02","duplicateCount":607,"likeCount":16,"commentCount":3,"version":"1"},{"date":"2021-12-03","duplicateCount":608,"likeCount":16,"commentCount":3,"version":"1"},{"date":"2021-12-04","duplicateCount":608,"likeCount":16,"commentCount":3,"version":"1"},{"date":"2021-12-05","duplicateCount":608,"likeCount":16,"commentCount":3,"version":"1"},{"date":"2021-12-06","duplicateCount":608,"likeCount":16,"commentCount":3,"version":"1"},{"date":"2021-12-07","duplicateCount":608,"likeCount":16,"commentCount":3,"version":"1"},{"date":"2021-12-08","duplicateCount":608,"likeCount":16,"commentCount":3,"version":"1"},{"date":"2021-12-09","duplicateCount":608,"likeCount":16,"commentCount":3,"version":"1"},{"date":"2021-12-10","duplicateCount":608,"likeCount":16,"commentCount":3,"version":"1"},{"date":"2021-12-11","duplicateCount":608,"likeCount":16,"commentCount":3,"version":"1"},{"date":"2021-12-12","duplicateCount":609,"likeCount":16,"commentCount":3,"version":"1"},{"date":"2021-12-13","duplicateCount":610,"likeCount":16,"commentCount":3,"version":"1"},{"date":"2021-12-14","duplicateCount":611,"likeCount":16,"commentCount":3,"version":"1"},{"date":"2021-12-15","duplicateCount":611,"likeCount":16,"commentCount":3,"version":"1"},{"date":"2021-12-16","duplicateCount":612,"likeCount":16,"commentCount":3,"version":"1"},{"date":"2021-12-17","duplicateCount":613,"likeCount":16,"commentCount":3,"version":"1"},{"date":"2021-12-18","duplicateCount":614,"likeCount":16,"commentCount":3,"version":"1"},{"date":"2021-12-19","duplicateCount":616,"likeCount":16,"commentCount":3,"version":"1"}]
