[{"date":"2021-10-16","duplicateCount":954,"likeCount":33,"viewCount":38873,"commentCount":0,"version":"5"},{"date":"2021-10-17","duplicateCount":956,"likeCount":33,"viewCount":38879,"commentCount":0,"version":"5"},{"date":"2021-10-18","duplicateCount":957,"likeCount":33,"viewCount":38888,"commentCount":0,"version":"5"},{"date":"2021-10-19","duplicateCount":959,"likeCount":33,"viewCount":38892,"commentCount":0,"version":"5"},{"date":"2021-10-20","duplicateCount":962,"likeCount":33,"viewCount":38898,"commentCount":0,"version":"5"},{"date":"2021-10-21","duplicateCount":967,"likeCount":33,"viewCount":38913,"commentCount":0,"version":"5"},{"date":"2021-10-22","duplicateCount":973,"likeCount":33,"viewCount":38926,"commentCount":0,"version":"5"},{"date":"2021-10-23","duplicateCount":975,"likeCount":33,"viewCount":38933,"commentCount":0,"version":"5"},{"date":"2021-10-24","duplicateCount":975,"likeCount":33,"viewCount":38935,"commentCount":0,"version":"5"},{"date":"2021-10-25","duplicateCount":976,"likeCount":33,"viewCount":38940,"commentCount":0,"version":"5"},{"date":"2021-10-26","duplicateCount":985,"likeCount":33,"viewCount":38957,"commentCount":0,"version":"5"},{"date":"2021-10-27","duplicateCount":988,"likeCount":33,"viewCount":38966,"commentCount":0,"version":"5"},{"date":"2021-10-28","duplicateCount":992,"likeCount":33,"viewCount":38971,"commentCount":0,"version":"5"},{"date":"2021-10-29","duplicateCount":998,"likeCount":33,"viewCount":38981,"commentCount":0,"version":"5"},{"date":"2021-10-30","duplicateCount":1000,"likeCount":33,"viewCount":38987,"commentCount":0,"version":"5"},{"date":"2021-10-31","duplicateCount":1002,"likeCount":33,"viewCount":38989,"commentCount":0,"version":"5"},{"date":"2021-11-01","duplicateCount":1008,"likeCount":33,"viewCount":39000,"commentCount":0,"version":"5"},{"date":"2021-11-02","duplicateCount":1013,"likeCount":33,"viewCount":39010,"commentCount":0,"version":"5"},{"date":"2021-11-03","duplicateCount":1015,"likeCount":33,"viewCount":39021,"commentCount":0,"version":"5"},{"date":"2021-11-04","duplicateCount":1018,"likeCount":33,"viewCount":39023,"commentCount":0,"version":"5"},{"date":"2021-11-05","duplicateCount":1024,"likeCount":33,"viewCount":39032,"commentCount":0,"version":"5"},{"date":"2021-11-06","duplicateCount":1027,"likeCount":33,"viewCount":39037,"commentCount":0,"version":"5"},{"date":"2021-11-07","duplicateCount":1031,"likeCount":33,"viewCount":39043,"commentCount":0,"version":"5"},{"date":"2021-11-08","duplicateCount":1033,"likeCount":34,"viewCount":39049,"commentCount":0,"version":"5"},{"date":"2021-11-09","duplicateCount":1036,"likeCount":34,"viewCount":39056,"commentCount":0,"version":"5"},{"date":"2021-11-10","duplicateCount":1037,"likeCount":34,"viewCount":39063,"commentCount":0,"version":"5"}]
