{"id":"966721560689337334","name":"Config 2021 Name Card & Agenda Builder (Community)","lastUpdateDate":"2021-04-21T15:26:21.031Z","publisherHandle":"josh044","publisherImage":"https://s3-alpha.figma.com/profile/6a317db9-c8c2-4a77-9cc9-c2524bbc274c","publisherId":"873680898687041591","publisherName":"Josh_Force","thumbnailUrl":"https://s3-alpha.figma.com/hub/file/803160104/2b488040-8646-47f1-86c2-e3398b44a5b3-cover.png","description":"","url":"https://www.figma.com/community/file/966721560689337334"}
