{"id":"1030115766369337636","name":"Billy’s and the Mysterious Island","lastUpdateDate":"2021-10-13T13:52:17.442Z","publisherHandle":"GuanRuey","publisherImage":"https://www.gravatar.com/avatar/dbf753b0f1c8230ee485342ec9555f17?size=240&default=https%3A%2F%2Fs3-alpha.figma.com%2Fstatic%2Fuser_h_v2.png","publisherId":"1025549948918272217","publisherName":"Huang T-One","thumbnailUrl":"https://s3-alpha.figma.com/hub/file/1204339651/2f316a1a-1b38-4665-afd8-bf3fd83a8b15-cover.png","description":"","url":"https://www.figma.com/community/file/1030115766369337636"}
