{"id":"1094281762105344937","name":"Sign Up | Daily 001","lastUpdateDate":"2022-04-08T15:25:03.096Z","publisherHandle":"sleyrz","publisherImage":"https://www.gravatar.com/avatar/67c1cd7d00270660ff25c005ed227995?size=240&default=https%3A%2F%2Fs3-alpha.figma.com%2Fstatic%2Fuser_m_v2.png","publisherId":"349205","publisherName":"Monika Kasperowicz","thumbnailUrl":"https://s3-alpha.figma.com/hub/file/1745182230/d0dceb8e-bade-42cc-b543-8572de137f22-cover.png","description":"","url":"https://www.figma.com/community/file/1094281762105344937"}
