{"id":"1043181886430789550","name":"Retro Firework Special","lastUpdateDate":"2021-11-18T15:12:23.224Z","publisherHandle":"danielyb","publisherImage":"https://www.gravatar.com/avatar/a288c7eab72983aba5fbc034f96a0539?size=240&default=https%3A%2F%2Fs3-alpha.figma.com%2Fstatic%2Fuser_d_v2.png","publisherId":"1009006906678738086","publisherName":"Daniel Yerbury-Brown","thumbnailUrl":"https://s3-alpha.figma.com/hub/file/1306638145/feafd35f-97ff-4478-95ec-c093c5b71281-cover.png","description":"","url":"https://www.figma.com/community/file/1043181886430789550"}
