[{"date":"2021-10-16","duplicateCount":60,"likeCount":3,"viewCount":3926,"commentCount":0,"version":"3"},{"date":"2021-10-17","duplicateCount":60,"likeCount":3,"viewCount":3928,"commentCount":0,"version":"3"},{"date":"2021-10-18","duplicateCount":61,"likeCount":3,"viewCount":3935,"commentCount":0,"version":"3"},{"date":"2021-10-19","duplicateCount":61,"likeCount":3,"viewCount":3937,"commentCount":0,"version":"3"},{"date":"2021-10-20","duplicateCount":61,"likeCount":3,"viewCount":3941,"commentCount":0,"version":"3"},{"date":"2021-10-21","duplicateCount":62,"likeCount":3,"viewCount":3944,"commentCount":0,"version":"3"},{"date":"2021-10-22","duplicateCount":62,"likeCount":3,"viewCount":3948,"commentCount":0,"version":"3"},{"date":"2021-10-23","duplicateCount":62,"likeCount":3,"viewCount":3949,"commentCount":0,"version":"3"},{"date":"2021-10-24","duplicateCount":65,"likeCount":3,"viewCount":3952,"commentCount":0,"version":"3"}]
