[{"date":"2022-04-30","duplicateCount":171,"likeCount":18,"commentCount":0,"version":"3"},{"date":"2022-05-01","duplicateCount":407,"likeCount":22,"commentCount":0,"version":"3"},{"date":"2022-05-02","duplicateCount":699,"likeCount":36,"commentCount":0,"version":"3"},{"date":"2022-05-03","duplicateCount":1170,"likeCount":57,"commentCount":0,"version":"3"},{"date":"2022-05-04","duplicateCount":1812,"likeCount":90,"commentCount":0,"version":"3"},{"date":"2022-05-05","duplicateCount":2461,"likeCount":127,"commentCount":0,"version":"3"},{"date":"2022-05-06","duplicateCount":3101,"likeCount":158,"commentCount":0,"version":"3"},{"date":"2022-05-07","duplicateCount":3531,"likeCount":171,"commentCount":0,"version":"3"},{"date":"2022-05-08","duplicateCount":3746,"likeCount":176,"commentCount":0,"version":"3"},{"date":"2022-05-09","duplicateCount":3964,"likeCount":180,"commentCount":0,"version":"3"},{"date":"2022-05-10","duplicateCount":4384,"likeCount":192,"commentCount":2,"version":"3"},{"date":"2022-05-11","duplicateCount":4782,"likeCount":205,"commentCount":2,"version":"3"},{"date":"2022-05-12","duplicateCount":5193,"likeCount":215,"commentCount":2,"version":"3"},{"date":"2022-05-13","duplicateCount":5582,"likeCount":224,"commentCount":2,"version":"3"},{"date":"2022-05-14","duplicateCount":5930,"likeCount":230,"commentCount":2,"version":"3"},{"date":"2022-05-15","duplicateCount":6163,"likeCount":233,"commentCount":2,"version":"3"},{"date":"2022-05-16","duplicateCount":6428,"likeCount":240,"commentCount":2,"version":"3"},{"date":"2022-05-17","duplicateCount":6867,"likeCount":258,"commentCount":2,"version":"3"},{"date":"2022-05-18","duplicateCount":7276,"likeCount":274,"commentCount":2,"version":"3"},{"date":"2022-05-19","duplicateCount":7665,"likeCount":288,"commentCount":2,"version":"3"},{"date":"2022-05-20","duplicateCount":7958,"likeCount":290,"commentCount":2,"version":"3"},{"date":"2022-05-21","duplicateCount":8137,"likeCount":294,"commentCount":2,"version":"3"},{"date":"2022-05-22","duplicateCount":8223,"likeCount":297,"commentCount":2,"version":"3"},{"date":"2022-05-23","duplicateCount":8340,"likeCount":307,"commentCount":2,"version":"3"},{"date":"2022-05-24","duplicateCount":8527,"likeCount":313,"commentCount":2,"version":"3"},{"date":"2022-05-25","duplicateCount":8697,"likeCount":316,"commentCount":2,"version":"3"},{"date":"2022-05-26","duplicateCount":8857,"likeCount":328,"commentCount":2,"version":"3"},{"date":"2022-05-27","duplicateCount":8976,"likeCount":334,"commentCount":2,"version":"3"},{"date":"2022-05-28","duplicateCount":9040,"likeCount":336,"commentCount":2,"version":"3"},{"date":"2022-05-29","duplicateCount":9076,"likeCount":336,"commentCount":2,"version":"3"},{"date":"2022-05-30","duplicateCount":9122,"likeCount":336,"commentCount":2,"version":"3"},{"date":"2022-05-31","duplicateCount":9170,"likeCount":338,"commentCount":4,"version":"3"},{"date":"2022-06-01","duplicateCount":9230,"likeCount":340,"commentCount":4,"version":"3"},{"date":"2022-06-02","duplicateCount":9296,"likeCount":346,"commentCount":4,"version":"5"},{"date":"2022-06-03","duplicateCount":9350,"likeCount":350,"commentCount":6,"version":"5"},{"date":"2022-06-04","duplicateCount":9392,"likeCount":352,"commentCount":7,"version":"5"},{"date":"2022-06-05","duplicateCount":9419,"likeCount":354,"commentCount":7,"version":"5"},{"date":"2022-06-06","duplicateCount":9449,"likeCount":355,"commentCount":7,"version":"5"},{"date":"2022-06-07","duplicateCount":9495,"likeCount":358,"commentCount":7,"version":"5"}]
