{"id":"1111404799581285446","name":"Text fields - Tida","lastUpdateDate":"2022-05-25T21:38:56.253Z","publisherHandle":"rahmani","publisherImage":"https://s3-alpha.figma.com/profile/49886bb6-020d-46ac-af3f-84b2b3639adb","publisherId":"1076534","publisherName":"Alireza Rahmani","thumbnailUrl":"https://s3-alpha.figma.com/hub/file/1913536131/5c0efd5d-99cf-4db6-9f58-b205cb627afa-cover.png","description":"<p><strong>Bidirectional interactive Text Fields components.</strong></p><p><br></p><p>🎨 Styles:</p><ul><li><strong>Filled</strong></li><li><strong>Outline</strong></li></ul><p><br></p><p>✨ Properties:</p><ul><li><strong>Filled</strong></li><li><strong>State</strong></li><li><strong>Size</strong></li><li><strong>Icon</strong></li><li><strong>Label</strong></li><li><strong>Value</strong></li></ul><p><br></p><p>we also tried to optimize the structure of the layers to create an standard Text Field component in figma.</p><p>💡 Feel free to share your ideas in comments!</p>","url":"https://www.figma.com/community/file/1111404799581285446"}
