[{"date":"2021-10-16","duplicateCount":750,"likeCount":26,"viewCount":40466,"commentCount":0,"version":"2"},{"date":"2021-10-17","duplicateCount":750,"likeCount":26,"viewCount":40467,"commentCount":0,"version":"2"},{"date":"2021-10-18","duplicateCount":752,"likeCount":26,"viewCount":40472,"commentCount":0,"version":"2"},{"date":"2021-10-19","duplicateCount":753,"likeCount":26,"viewCount":40480,"commentCount":0,"version":"2"},{"date":"2021-10-20","duplicateCount":757,"likeCount":26,"viewCount":40493,"commentCount":0,"version":"2"},{"date":"2021-10-21","duplicateCount":758,"likeCount":26,"viewCount":40500,"commentCount":0,"version":"2"},{"date":"2021-10-22","duplicateCount":760,"likeCount":26,"viewCount":40506,"commentCount":0,"version":"2"},{"date":"2021-10-23","duplicateCount":762,"likeCount":26,"viewCount":40517,"commentCount":0,"version":"2"},{"date":"2021-10-24","duplicateCount":762,"likeCount":26,"viewCount":40522,"commentCount":0,"version":"2"},{"date":"2021-10-25","duplicateCount":764,"likeCount":26,"viewCount":40527,"commentCount":0,"version":"2"},{"date":"2021-10-26","duplicateCount":770,"likeCount":26,"viewCount":40538,"commentCount":0,"version":"2"},{"date":"2021-10-27","duplicateCount":776,"likeCount":27,"viewCount":40550,"commentCount":0,"version":"2"},{"date":"2021-10-28","duplicateCount":782,"likeCount":28,"viewCount":40566,"commentCount":0,"version":"2"},{"date":"2021-10-29","duplicateCount":791,"likeCount":29,"viewCount":40587,"commentCount":0,"version":"2"},{"date":"2021-10-30","duplicateCount":794,"likeCount":29,"viewCount":40595,"commentCount":0,"version":"2"},{"date":"2021-10-31","duplicateCount":798,"likeCount":29,"viewCount":40604,"commentCount":0,"version":"2"},{"date":"2021-11-01","duplicateCount":799,"likeCount":29,"viewCount":40611,"commentCount":0,"version":"2"},{"date":"2021-11-02","duplicateCount":807,"likeCount":29,"viewCount":40629,"commentCount":0,"version":"2"},{"date":"2021-11-03","duplicateCount":811,"likeCount":29,"viewCount":40643,"commentCount":0,"version":"2"},{"date":"2021-11-04","duplicateCount":816,"likeCount":29,"viewCount":40657,"commentCount":0,"version":"2"},{"date":"2021-11-05","duplicateCount":818,"likeCount":29,"viewCount":40662,"commentCount":0,"version":"2"},{"date":"2021-11-06","duplicateCount":819,"likeCount":29,"viewCount":40671,"commentCount":0,"version":"2"},{"date":"2021-11-07","duplicateCount":819,"likeCount":29,"viewCount":40671,"commentCount":0,"version":"2"},{"date":"2021-11-08","duplicateCount":819,"likeCount":29,"viewCount":40673,"commentCount":0,"version":"2"},{"date":"2021-11-09","duplicateCount":821,"likeCount":29,"viewCount":40682,"commentCount":0,"version":"2"},{"date":"2021-11-10","duplicateCount":828,"likeCount":30,"viewCount":40697,"commentCount":0,"version":"2"},{"date":"2021-11-11","duplicateCount":830,"likeCount":30,"viewCount":40705,"commentCount":0,"version":"2"},{"date":"2021-11-12","duplicateCount":834,"likeCount":30,"viewCount":40713,"commentCount":0,"version":"2"},{"date":"2021-11-13","duplicateCount":838,"likeCount":30,"viewCount":2034,"commentCount":0,"version":"2"},{"date":"2021-11-14","duplicateCount":839,"likeCount":31,"viewCount":2043,"commentCount":0,"version":"2"},{"date":"2021-11-15","duplicateCount":841,"likeCount":31,"viewCount":2050,"commentCount":0,"version":"2"},{"date":"2021-11-16","duplicateCount":843,"likeCount":31,"viewCount":2056,"commentCount":0,"version":"2"},{"date":"2021-11-17","duplicateCount":845,"likeCount":32,"viewCount":2067,"commentCount":0,"version":"2"},{"date":"2021-11-18","duplicateCount":848,"likeCount":32,"viewCount":2078,"commentCount":0,"version":"2"},{"date":"2021-11-19","duplicateCount":855,"likeCount":32,"viewCount":2089,"commentCount":0,"version":"2"},{"date":"2021-11-20","duplicateCount":858,"likeCount":32,"viewCount":2096,"commentCount":0,"version":"2"},{"date":"2021-11-21","duplicateCount":859,"likeCount":32,"viewCount":2105,"commentCount":0,"version":"2"},{"date":"2021-11-22","duplicateCount":859,"likeCount":32,"viewCount":2107,"commentCount":0,"version":"2"},{"date":"2021-11-23","duplicateCount":867,"likeCount":32,"viewCount":2122,"commentCount":0,"version":"2"},{"date":"2021-11-24","duplicateCount":872,"likeCount":32,"commentCount":0,"version":"2"},{"date":"2021-11-25","duplicateCount":875,"likeCount":33,"commentCount":0,"version":"2"},{"date":"2021-11-26","duplicateCount":881,"likeCount":33,"commentCount":0,"version":"2"},{"date":"2021-11-27","duplicateCount":885,"likeCount":33,"commentCount":0,"version":"2"},{"date":"2021-11-28","duplicateCount":885,"likeCount":33,"commentCount":0,"version":"2"},{"date":"2021-11-29","duplicateCount":886,"likeCount":33,"commentCount":0,"version":"2"},{"date":"2021-11-30","duplicateCount":895,"likeCount":33,"commentCount":0,"version":"2"},{"date":"2021-12-01","duplicateCount":897,"likeCount":33,"commentCount":0,"version":"2"},{"date":"2021-12-02","duplicateCount":900,"likeCount":33,"commentCount":0,"version":"2"},{"date":"2021-12-03","duplicateCount":903,"likeCount":33,"commentCount":0,"version":"2"},{"date":"2021-12-04","duplicateCount":904,"likeCount":33,"commentCount":0,"version":"2"},{"date":"2021-12-05","duplicateCount":907,"likeCount":33,"commentCount":0,"version":"2"},{"date":"2021-12-06","duplicateCount":908,"likeCount":33,"commentCount":0,"version":"2"},{"date":"2021-12-07","duplicateCount":910,"likeCount":33,"commentCount":0,"version":"2"},{"date":"2021-12-08","duplicateCount":915,"likeCount":33,"commentCount":0,"version":"2"},{"date":"2021-12-09","duplicateCount":918,"likeCount":33,"commentCount":0,"version":"2"},{"date":"2021-12-10","duplicateCount":921,"likeCount":33,"commentCount":0,"version":"2"},{"date":"2021-12-11","duplicateCount":923,"likeCount":33,"commentCount":0,"version":"2"},{"date":"2021-12-12","duplicateCount":924,"likeCount":33,"commentCount":0,"version":"2"},{"date":"2021-12-13","duplicateCount":925,"likeCount":33,"commentCount":0,"version":"2"},{"date":"2021-12-14","duplicateCount":930,"likeCount":33,"commentCount":0,"version":"2"},{"date":"2021-12-15","duplicateCount":937,"likeCount":33,"commentCount":0,"version":"2"},{"date":"2021-12-16","duplicateCount":943,"likeCount":33,"commentCount":0,"version":"2"},{"date":"2021-12-17","duplicateCount":945,"likeCount":33,"commentCount":0,"version":"2"},{"date":"2021-12-18","duplicateCount":945,"likeCount":33,"commentCount":0,"version":"2"},{"date":"2021-12-19","duplicateCount":945,"likeCount":33,"commentCount":0,"version":"2"},{"date":"2021-12-20","duplicateCount":947,"likeCount":34,"commentCount":0,"version":"2"},{"date":"2021-12-21","duplicateCount":954,"likeCount":34,"commentCount":0,"version":"2"},{"date":"2021-12-22","duplicateCount":957,"likeCount":34,"commentCount":0,"version":"2"},{"date":"2021-12-23","duplicateCount":959,"likeCount":34,"commentCount":0,"version":"2"},{"date":"2021-12-24","duplicateCount":960,"likeCount":34,"commentCount":0,"version":"2"},{"date":"2021-12-25","duplicateCount":961,"likeCount":34,"commentCount":0,"version":"2"},{"date":"2021-12-26","duplicateCount":961,"likeCount":34,"commentCount":0,"version":"2"},{"date":"2021-12-28","duplicateCount":966,"likeCount":34,"commentCount":0,"version":"2"},{"date":"2021-12-29","duplicateCount":969,"likeCount":35,"commentCount":0,"version":"2"},{"date":"2021-12-30","duplicateCount":971,"likeCount":35,"commentCount":0,"version":"2"},{"date":"2021-12-31","duplicateCount":973,"likeCount":35,"commentCount":0,"version":"2"},{"date":"2022-01-01","duplicateCount":975,"likeCount":36,"commentCount":0,"version":"2"}]
