{"id":"1087964309728797206","name":"WL Home page","lastUpdateDate":"2022-03-22T05:01:44.992Z","publisherHandle":"krishnan","publisherImage":"https://www.gravatar.com/avatar/70c17e8d5921b337c70d02520c3a1566?size=240&default=https%3A%2F%2Fs3-alpha.figma.com%2Fstatic%2Fuser_k_v2.png","publisherId":"862937177392681988","publisherName":"Krishnan","thumbnailUrl":"https://s3-alpha.figma.com/hub/file/1677142007/53a654b0-e419-41c4-be97-2f53cc4296f2-cover.png","description":"","url":"https://www.figma.com/community/file/1087964309728797206"}
