{"id":"1066394405972919748","name":"CV","lastUpdateDate":"2022-01-21T16:30:39.201Z","publisherHandle":"armelguerin","publisherImage":"https://www.gravatar.com/avatar/e31c64ec523fb6d1769338e2c8ce6513?size=240&default=https%3A%2F%2Fs3-alpha.figma.com%2Fstatic%2Fuser_a_v2.png","publisherId":"1038862921451119859","publisherName":"armel guerin","thumbnailUrl":"https://s3-alpha.figma.com/hub/file/1480164049/0430c5f4-e8eb-4679-8c4f-2cdfe90f2b12-cover.png","description":"<p>simple cv</p>","url":"https://www.figma.com/community/file/1066394405972919748"}
