{"id":"985642643750819404","name":"Cool Hover Effect","lastUpdateDate":"2021-07-03T16:11:11.362Z","publisherHandle":"dan91ish","publisherImage":"https://s3-alpha.figma.com/profile/eadfe69b-ade7-4bf9-88b5-17abf84a661b","publisherId":"1355508","publisherName":"Muhammad Danish","thumbnailUrl":"https://s3-alpha.figma.com/hub/file/956793787/48ebfd64-4eb4-421a-8fbd-4898429b50d0-cover.png","description":"<p>Checkout the cool hover effect I made in using Figma Prototyping</p>","url":"https://www.figma.com/community/file/985642643750819404"}
