{"id":"1101107691539044678","name":"Gestion laivraison","lastUpdateDate":"2022-04-27T11:28:51.386Z","publisherHandle":"2fd74586_37fc_4","publisherImage":"https://www.gravatar.com/avatar/aa7a48c66473a97db541bae2212ea791?size=240&default=https%3A%2F%2Fs3-alpha.figma.com%2Fstatic%2Fuser_m_v2.png","publisherId":"934545029570563186","publisherName":"Mokhtar","thumbnailUrl":"https://s3-alpha.figma.com/hub/file/1765385281/89f6ff25-5b1d-40d1-85ba-b1b6014d6fca-cover.png","description":"","url":"https://www.figma.com/community/file/1101107691539044678"}
