{"id":"1023511567823285670","name":"Making products better activity","lastUpdateDate":"2021-09-26T09:11:41.189Z","publisherHandle":"ux_anudeep","publisherImage":"https://s3-alpha.figma.com/profile/5c20517e-c6a1-4e5f-9fef-db45ad3b7e99","publisherId":"955538792482006640","publisherName":"UX Anudeep","thumbnailUrl":"https://s3-alpha.figma.com/hub/file/1156763367/c1942ffd-a251-47ff-8671-a7b1f396e521-cover.png","description":"<p>In this activity we will understand important steps involved in making a product better in a non-textbook way</p>","url":"https://www.figma.com/community/file/1023511567823285670"}
