{"id":"1079943353203902935","name":"Quotes 2.0","lastUpdateDate":"2022-02-28T01:49:19.868Z","publisherHandle":"marcelocamargo","publisherImage":"https://www.gravatar.com/avatar/00a387e8c24005273504cc06596b2cb5?size=240&default=https%3A%2F%2Fs3-alpha.figma.com%2Fstatic%2Fuser_m_v2.png","publisherId":"939298014439787203","publisherName":"Marcelo Camargo","thumbnailUrl":"https://s3-alpha.figma.com/hub/file/1598551771/e0de6561-798e-47c5-8bc8-52452616b5bc-cover.png","description":"","url":"https://www.figma.com/community/file/1079943353203902935"}
