{"id":"1109523209661018743","name":"会员","lastUpdateDate":"2022-05-20T16:49:07.239Z","publisherHandle":"9596f64d_b4ce_4","publisherImage":"https://www.gravatar.com/avatar/93bcfef2cfd861954e3503245f9e2353?size=240&default=https%3A%2F%2Fs3-alpha.figma.com%2Fstatic%2Fuser_g_v2.png","publisherId":"1073313603161184672","publisherName":"Gapper","thumbnailUrl":"https://s3-alpha.figma.com/hub/file/1894896523/8170831b-9c76-4bee-816c-45a2d60bbb7f-cover.png","description":"","url":"https://www.figma.com/community/file/1109523209661018743"}
