{"id":"995771759885392251","name":"Verse - Payment Dashboard UI Kit","lastUpdateDate":"2021-07-10T19:39:18.792Z","publisherHandle":"uiwithpourya","publisherImage":"https://s3-alpha.figma.com/profile/feba0ec7-1a85-4004-8feb-ee615065f677","publisherId":"918563209685532723","publisherName":"Pourya Zamani","thumbnailUrl":"https://s3-alpha.figma.com/hub/file/971812245/c49c389a-3fd9-4249-b4b5-5c731636d2c4-cover.png","description":"<p>Hello Guys 🔥&nbsp;</p><p>I would like to share with you Verse - Payment Dashboard that it designed both in light and dark version.</p><p>Hope you enjoyed it.&nbsp;</p><p><br></p><p>Don't forget to share with others</p><p><br></p><p>Source: </p><p>Cards: https://www.figma.com/@simmmple</p><p>Icons:  https://www.figma.com/@piqodesign</p><p>charts: https://www.figma.com/@uiwithpourya</p>","url":"https://www.figma.com/community/file/995771759885392251"}
