{"id":"1039897280961071792","name":"Wireframes course","lastUpdateDate":"2021-11-09T13:40:32.267Z","publisherHandle":"McDelli","publisherImage":"https://www.gravatar.com/avatar/9fd1fb340eb2f5f63f3462592ff3d0d4?size=240&default=https%3A%2F%2Fs3-alpha.figma.com%2Fstatic%2Fuser_m_v2.png","publisherId":"979077336025556110","publisherName":"Marco Delli Carri","thumbnailUrl":"https://s3-alpha.figma.com/hub/file/1277501198/0a21669d-c5e0-45bb-9161-b0b5bfbd37ad-cover.png","description":"","url":"https://www.figma.com/community/file/1039897280961071792"}
