{"id":"1104602262173143817","name":"Config 2022 Name Card - [Julie Jamolo]","lastUpdateDate":"2022-05-07T02:55:13.636Z","publisherHandle":"juliejamolo","publisherImage":"https://www.gravatar.com/avatar/4db4719aa8dc74a1ac1c960f6e254340?size=240&default=https%3A%2F%2Fs3-alpha.figma.com%2Fstatic%2Fuser_j_v2.png","publisherId":"2536939","publisherName":"Julie Jamolo","thumbnailUrl":"https://s3-alpha.figma.com/hub/file/1842926173/9d3c4df3-75ff-4589-a9f1-6b1f759f7c1c-cover.png","description":"<p><br></p>","url":"https://www.figma.com/community/file/1104602262173143817"}
