{"id":"966358300249414001","name":"Config 2021 Name Card - Jeroen Callewaert","lastUpdateDate":"2021-04-20T15:22:52.959Z","publisherHandle":"jecaj","publisherImage":"https://s3-alpha.figma.com/profile/039546d9-fe60-4810-98b9-a5fa5e6fb205","publisherId":"948225959394685290","publisherName":"Jeroen Callewaert","thumbnailUrl":"https://s3-alpha.figma.com/hub/file/800455957/06a370ac-c5b7-4f21-950d-95fd96293824-cover.png","description":"","url":"https://www.figma.com/community/file/966358300249414001"}
