[{"date":"2021-10-16","duplicateCount":63,"likeCount":7,"viewCount":2684,"commentCount":0,"version":"1"},{"date":"2021-10-17","duplicateCount":66,"likeCount":7,"viewCount":2689,"commentCount":0,"version":"1"},{"date":"2021-10-18","duplicateCount":68,"likeCount":7,"viewCount":2701,"commentCount":0,"version":"1"},{"date":"2021-10-19","duplicateCount":70,"likeCount":7,"viewCount":2713,"commentCount":0,"version":"1"},{"date":"2021-10-21","duplicateCount":74,"likeCount":7,"viewCount":2724,"commentCount":0,"version":"1"},{"date":"2021-10-22","duplicateCount":76,"likeCount":7,"viewCount":2732,"commentCount":0,"version":"1"},{"date":"2021-10-23","duplicateCount":76,"likeCount":7,"viewCount":2737,"commentCount":0,"version":"1"},{"date":"2021-10-24","duplicateCount":77,"likeCount":7,"viewCount":2741,"commentCount":0,"version":"1"},{"date":"2021-10-25","duplicateCount":78,"likeCount":7,"viewCount":2743,"commentCount":0,"version":"1"},{"date":"2021-10-26","duplicateCount":79,"likeCount":7,"viewCount":2753,"commentCount":0,"version":"1"},{"date":"2021-10-27","duplicateCount":80,"likeCount":7,"viewCount":2763,"commentCount":0,"version":"1"},{"date":"2021-10-28","duplicateCount":85,"likeCount":8,"viewCount":2776,"commentCount":0,"version":"1"},{"date":"2021-10-29","duplicateCount":85,"likeCount":8,"viewCount":2783,"commentCount":0,"version":"1"},{"date":"2021-10-30","duplicateCount":87,"likeCount":8,"viewCount":2790,"commentCount":0,"version":"1"},{"date":"2021-10-31","duplicateCount":89,"likeCount":8,"viewCount":2794,"commentCount":0,"version":"1"},{"date":"2021-11-01","duplicateCount":89,"likeCount":8,"viewCount":2798,"commentCount":0,"version":"1"},{"date":"2021-11-02","duplicateCount":92,"likeCount":8,"viewCount":2808,"commentCount":0,"version":"1"},{"date":"2021-11-03","duplicateCount":96,"likeCount":8,"viewCount":2818,"commentCount":0,"version":"1"},{"date":"2021-11-04","duplicateCount":99,"likeCount":8,"viewCount":2823,"commentCount":0,"version":"1"},{"date":"2021-11-05","duplicateCount":102,"likeCount":8,"viewCount":2831,"commentCount":0,"version":"1"},{"date":"2021-11-06","duplicateCount":104,"likeCount":8,"viewCount":2836,"commentCount":0,"version":"1"},{"date":"2021-11-07","duplicateCount":107,"likeCount":9,"viewCount":2841,"commentCount":0,"version":"1"},{"date":"2021-11-08","duplicateCount":108,"likeCount":9,"viewCount":2843,"commentCount":0,"version":"1"},{"date":"2021-11-09","duplicateCount":111,"likeCount":10,"viewCount":2853,"commentCount":0,"version":"1"},{"date":"2021-11-10","duplicateCount":113,"likeCount":10,"viewCount":2865,"commentCount":0,"version":"1"},{"date":"2021-11-11","duplicateCount":119,"likeCount":10,"viewCount":2882,"commentCount":0,"version":"1"},{"date":"2021-11-12","duplicateCount":123,"likeCount":10,"viewCount":2892,"commentCount":0,"version":"1"},{"date":"2021-11-13","duplicateCount":126,"likeCount":10,"viewCount":348,"commentCount":0,"version":"1"},{"date":"2021-11-14","duplicateCount":127,"likeCount":10,"viewCount":353,"commentCount":0,"version":"1"},{"date":"2021-11-15","duplicateCount":127,"likeCount":10,"viewCount":358,"commentCount":0,"version":"1"},{"date":"2021-11-16","duplicateCount":130,"likeCount":10,"viewCount":365,"commentCount":0,"version":"1"},{"date":"2021-11-17","duplicateCount":133,"likeCount":10,"viewCount":376,"commentCount":0,"version":"1"},{"date":"2021-11-18","duplicateCount":133,"likeCount":10,"viewCount":385,"commentCount":0,"version":"1"},{"date":"2021-11-19","duplicateCount":133,"likeCount":10,"viewCount":392,"commentCount":0,"version":"1"},{"date":"2021-11-20","duplicateCount":134,"likeCount":10,"viewCount":397,"commentCount":0,"version":"1"},{"date":"2021-11-21","duplicateCount":136,"likeCount":10,"viewCount":402,"commentCount":0,"version":"1"},{"date":"2021-11-22","duplicateCount":136,"likeCount":10,"viewCount":403,"commentCount":0,"version":"1"},{"date":"2021-11-23","duplicateCount":139,"likeCount":10,"viewCount":412,"commentCount":0,"version":"1"},{"date":"2021-11-24","duplicateCount":140,"likeCount":10,"commentCount":0,"version":"1"},{"date":"2021-11-25","duplicateCount":142,"likeCount":10,"commentCount":0,"version":"1"},{"date":"2021-11-26","duplicateCount":148,"likeCount":10,"commentCount":0,"version":"1"},{"date":"2021-11-27","duplicateCount":150,"likeCount":10,"commentCount":0,"version":"1"},{"date":"2021-11-28","duplicateCount":153,"likeCount":10,"commentCount":0,"version":"1"},{"date":"2021-11-29","duplicateCount":153,"likeCount":10,"commentCount":0,"version":"1"},{"date":"2021-11-30","duplicateCount":153,"likeCount":10,"commentCount":0,"version":"1"},{"date":"2021-12-01","duplicateCount":155,"likeCount":10,"commentCount":0,"version":"1"},{"date":"2021-12-02","duplicateCount":155,"likeCount":10,"commentCount":0,"version":"1"},{"date":"2021-12-03","duplicateCount":156,"likeCount":10,"commentCount":0,"version":"1"},{"date":"2021-12-04","duplicateCount":156,"likeCount":10,"commentCount":0,"version":"1"},{"date":"2021-12-05","duplicateCount":156,"likeCount":10,"commentCount":0,"version":"1"},{"date":"2021-12-06","duplicateCount":157,"likeCount":10,"commentCount":0,"version":"1"},{"date":"2021-12-07","duplicateCount":158,"likeCount":10,"commentCount":0,"version":"1"},{"date":"2021-12-08","duplicateCount":160,"likeCount":10,"commentCount":0,"version":"1"},{"date":"2021-12-09","duplicateCount":163,"likeCount":10,"commentCount":0,"version":"1"},{"date":"2021-12-10","duplicateCount":165,"likeCount":10,"commentCount":0,"version":"1"},{"date":"2021-12-11","duplicateCount":166,"likeCount":10,"commentCount":0,"version":"1"},{"date":"2021-12-12","duplicateCount":167,"likeCount":10,"commentCount":0,"version":"1"},{"date":"2021-12-13","duplicateCount":168,"likeCount":10,"commentCount":0,"version":"1"},{"date":"2021-12-14","duplicateCount":173,"likeCount":10,"commentCount":0,"version":"1"},{"date":"2021-12-15","duplicateCount":174,"likeCount":10,"commentCount":0,"version":"1"},{"date":"2021-12-16","duplicateCount":175,"likeCount":10,"commentCount":0,"version":"1"},{"date":"2021-12-17","duplicateCount":176,"likeCount":10,"commentCount":0,"version":"1"},{"date":"2021-12-18","duplicateCount":176,"likeCount":10,"commentCount":0,"version":"1"},{"date":"2021-12-19","duplicateCount":176,"likeCount":10,"commentCount":0,"version":"1"},{"date":"2021-12-20","duplicateCount":176,"likeCount":10,"commentCount":0,"version":"1"},{"date":"2021-12-21","duplicateCount":176,"likeCount":10,"commentCount":0,"version":"1"},{"date":"2021-12-22","duplicateCount":177,"likeCount":10,"commentCount":0,"version":"1"},{"date":"2021-12-23","duplicateCount":179,"likeCount":10,"commentCount":0,"version":"1"},{"date":"2021-12-24","duplicateCount":179,"likeCount":10,"commentCount":0,"version":"1"},{"date":"2021-12-25","duplicateCount":180,"likeCount":10,"commentCount":0,"version":"1"},{"date":"2021-12-26","duplicateCount":183,"likeCount":10,"commentCount":0,"version":"1"},{"date":"2021-12-28","duplicateCount":184,"likeCount":10,"commentCount":0,"version":"1"},{"date":"2021-12-29","duplicateCount":185,"likeCount":10,"commentCount":0,"version":"1"},{"date":"2021-12-30","duplicateCount":185,"likeCount":10,"commentCount":0,"version":"1"},{"date":"2021-12-31","duplicateCount":186,"likeCount":10,"commentCount":0,"version":"1"},{"date":"2022-01-01","duplicateCount":186,"likeCount":10,"commentCount":0,"version":"1"},{"date":"2022-01-02","duplicateCount":186,"likeCount":10,"commentCount":0,"version":"1"},{"date":"2022-01-03","duplicateCount":187,"likeCount":10,"commentCount":0,"version":"1"},{"date":"2022-01-04","duplicateCount":187,"likeCount":10,"commentCount":0,"version":"1"},{"date":"2022-01-05","duplicateCount":190,"likeCount":10,"commentCount":0,"version":"1"},{"date":"2022-01-06","duplicateCount":190,"likeCount":10,"commentCount":0,"version":"1"},{"date":"2022-01-07","duplicateCount":190,"likeCount":10,"commentCount":0,"version":"1"},{"date":"2022-01-08","duplicateCount":191,"likeCount":10,"commentCount":0,"version":"1"},{"date":"2022-01-09","duplicateCount":191,"likeCount":10,"commentCount":0,"version":"1"},{"date":"2022-01-10","duplicateCount":191,"likeCount":10,"commentCount":0,"version":"1"},{"date":"2022-01-11","duplicateCount":194,"likeCount":10,"commentCount":0,"version":"1"},{"date":"2022-01-12","duplicateCount":196,"likeCount":11,"commentCount":0,"version":"1"},{"date":"2022-01-13","duplicateCount":197,"likeCount":12,"commentCount":0,"version":"1"},{"date":"2022-01-14","duplicateCount":198,"likeCount":12,"commentCount":0,"version":"1"},{"date":"2022-01-15","duplicateCount":199,"likeCount":12,"commentCount":0,"version":"1"},{"date":"2022-01-16","duplicateCount":200,"likeCount":12,"commentCount":0,"version":"1"},{"date":"2022-01-17","duplicateCount":200,"likeCount":12,"commentCount":0,"version":"1"},{"date":"2022-01-18","duplicateCount":204,"likeCount":14,"commentCount":0,"version":"1"},{"date":"2022-01-19","duplicateCount":205,"likeCount":14,"commentCount":0,"version":"1"},{"date":"2022-01-20","duplicateCount":209,"likeCount":15,"commentCount":0,"version":"1"},{"date":"2022-01-21","duplicateCount":210,"likeCount":15,"commentCount":0,"version":"1"},{"date":"2022-01-22","duplicateCount":211,"likeCount":15,"commentCount":0,"version":"1"},{"date":"2022-01-23","duplicateCount":212,"likeCount":15,"commentCount":0,"version":"1"},{"date":"2022-01-24","duplicateCount":213,"likeCount":15,"commentCount":0,"version":"1"},{"date":"2022-01-25","duplicateCount":213,"likeCount":15,"commentCount":0,"version":"1"},{"date":"2022-01-26","duplicateCount":213,"likeCount":15,"commentCount":0,"version":"1"},{"date":"2022-01-27","duplicateCount":214,"likeCount":15,"commentCount":0,"version":"1"},{"date":"2022-01-28","duplicateCount":215,"likeCount":15,"commentCount":0,"version":"1"},{"date":"2022-01-29","duplicateCount":215,"likeCount":15,"commentCount":0,"version":"1"},{"date":"2022-01-30","duplicateCount":216,"likeCount":15,"commentCount":0,"version":"1"},{"date":"2022-01-31","duplicateCount":218,"likeCount":15,"commentCount":0,"version":"1"},{"date":"2022-02-01","duplicateCount":218,"likeCount":15,"commentCount":0,"version":"1"},{"date":"2022-02-02","duplicateCount":220,"likeCount":15,"commentCount":0,"version":"1"},{"date":"2022-02-03","duplicateCount":220,"likeCount":15,"commentCount":0,"version":"1"},{"date":"2022-02-04","duplicateCount":221,"likeCount":15,"commentCount":0,"version":"1"},{"date":"2022-03-31","duplicateCount":281,"likeCount":19,"commentCount":0,"version":"1"},{"date":"2022-04-01","duplicateCount":281,"likeCount":19,"commentCount":0,"version":"1"},{"date":"2022-04-02","duplicateCount":283,"likeCount":19,"commentCount":0,"version":"1"},{"date":"2022-04-03","duplicateCount":285,"likeCount":19,"commentCount":0,"version":"1"},{"date":"2022-04-04","duplicateCount":285,"likeCount":19,"commentCount":0,"version":"1"},{"date":"2022-04-05","duplicateCount":285,"likeCount":19,"commentCount":0,"version":"1"},{"date":"2022-04-06","duplicateCount":286,"likeCount":19,"commentCount":0,"version":"1"},{"date":"2022-04-07","duplicateCount":289,"likeCount":19,"commentCount":0,"version":"1"}]
