[{"date":"2021-10-16","installCount":401,"likeCount":18,"viewCount":33159,"commentCount":17,"version":"17"},{"date":"2021-10-17","installCount":404,"likeCount":18,"viewCount":33161,"commentCount":17,"version":"17"},{"date":"2021-10-18","installCount":407,"likeCount":18,"viewCount":33178,"commentCount":17,"version":"17"},{"date":"2021-10-19","installCount":414,"likeCount":18,"viewCount":33195,"commentCount":17,"version":"17"},{"date":"2021-10-20","installCount":421,"likeCount":18,"viewCount":33220,"commentCount":17,"version":"17"},{"date":"2021-10-21","installCount":426,"likeCount":19,"viewCount":33240,"commentCount":17,"version":"17"},{"date":"2021-10-22","installCount":432,"likeCount":20,"viewCount":33257,"commentCount":17,"version":"17"},{"date":"2021-10-23","installCount":434,"likeCount":21,"viewCount":33267,"commentCount":17,"version":"17"}]
