{"id":"1083382262832199158","name":"Chinese Live User Journey","lastUpdateDate":"2022-03-09T13:41:16.439Z","publisherHandle":"LingoaceProduct","publisherImage":"https://www.gravatar.com/avatar/32a81640eb00bbbe9c3e074095b40f7c?size=240&default=https%3A%2F%2Fs3-alpha.figma.com%2Fstatic%2Fuser_z_v2.png","publisherId":"1060822495954308966","publisherName":"ZhangCe","thumbnailUrl":"https://s3-alpha.figma.com/hub/file/1632501612/c4b1fbbc-f795-49e5-8474-069a6dd3dbb7-cover.png","description":"","url":"https://www.figma.com/community/file/1083382262832199158"}
