{"id":"1009728454881721702","name":"Hope UI Admin | Free Open Source Bootstrap 5 Admin Template","lastUpdateDate":"2021-09-18T09:13:02.188Z","publisherHandle":"Iqonicdesigns","publisherImage":"https://s3-alpha.figma.com/profile/06fd6272-1d76-439b-b4d2-c5f82673aae6","publisherId":"969861792205499232","publisherName":"Iqonic Design","thumbnailUrl":"https://s3-alpha.figma.com/hub/file/1138881707/454e6ff1-816b-4c96-8a9b-0316516c91d3-cover.png","description":"<p>Hope UI –&nbsp;<strong>Free open source Bootstrap 5 Admin Template</strong>&nbsp;is a gorgeously built pre-designed admin dashboard template.</p><p><br></p><p><strong>LIVE DEMO</strong><a href=\"https://templates.iqonic.design/hope-ui/html/dist/dashboard/\" rel=\"noreferrer noopener nofollow\" target=\"_blank\"><strong> </strong></a>: <a href=\"https://templates.iqonic.design/hope-ui/html/dist/dashboard/\" rel=\"noreferrer noopener nofollow\" target=\"_blank\">Click Here</a></p><p><strong>DOWNLOAD FULL CODE </strong>: <a href=\"https://bit.ly/2UrhMlZ\" rel=\"noreferrer noopener nofollow\" target=\"_blank\">Click Here </a></p><p><strong>AVAILABLE IN</strong> : <a href=\"https://bit.ly/3llDrFV\" rel=\"noreferrer noopener nofollow\" target=\"_blank\">HTML</a> + <a href=\"https://bit.ly/3l4enTv\" rel=\"noreferrer noopener nofollow\" target=\"_blank\">VUE JS</a> + <a href=\"https://bit.ly/3tp4Ium\" rel=\"noreferrer noopener nofollow\" target=\"_blank\">LARAVEL</a> +<a href=\"https://bit.ly/3tmznJ0\" rel=\"noreferrer noopener nofollow\" target=\"_blank\"> REACT JS</a></p><p><br></p><p>Hope UI is one of our finest design system and admin template which we have crafted after several months of efforts. This&nbsp;best free Bootstrap 5 admin template&nbsp;is fully responsive and user-friendly, allowing Hope UI users to work effortlessly.</p><p><br></p><p>Follow Us for get more free Items.</p><p><a href=\"https://bit.ly/3rTeLau\" rel=\"noreferrer noopener nofollow\" target=\"_blank\">www.iqonic.design</a></p><p><br></p><p><a href=\"https://dribbble.com/IqonicDesign\" rel=\"noreferrer noopener nofollow\" target=\"_blank\">Dribbble</a> | <a href=\"https://www.behance.net/iqonicdesign?tracking_source=search_projects_recommended%7Ciqonic%20design\" rel=\"noreferrer noopener nofollow\" target=\"_blank\">Behance </a> | <a href=\"https://www.facebook.com/iqonicdesign/\" rel=\"noreferrer noopener nofollow\" target=\"_blank\">Facebook </a> | <a href=\"https://www.instagram.com/iqonicdesign/\" rel=\"noreferrer noopener nofollow\" target=\"_blank\">Instagram</a></p>","url":"https://www.figma.com/community/file/1009728454881721702"}
