{"id":"1009767812083124600","name":"Graphic Design Collection 2021","lastUpdateDate":"2021-08-18T10:16:47.134Z","publisherHandle":"hopechen","publisherImage":"https://s3-alpha.figma.com/profile/1cec99a4-52eb-4661-af79-641e2fd00215","publisherId":"2888541","publisherName":"hope chen","thumbnailUrl":"https://s3-alpha.figma.com/hub/file/1061071253/c9a524e8-24c9-475c-aaef-de834fc68ffb-cover.png","description":"<p>Some graphic works including brochures, whitepaper cover design</p>","url":"https://www.figma.com/community/file/1009767812083124600"}
