{"id":"1106203309697497807","name":"Coinbase Support Phone Number +1844-4241―275  Support Number's team library","lastUpdateDate":"2022-05-11T12:57:01.415Z","publisherHandle":"coinbasesuport1","publisherImage":"https://www.gravatar.com/avatar/a33874f3babc705e134d500c67b4435f?size=240&default=https%3A%2F%2Fs3-alpha.figma.com%2Fstatic%2Fuser_c_v2.png","publisherId":"1106202929811570031","publisherName":"Coinbase Support Phone Number +1844-4241―275  Support Number","thumbnailUrl":"https://s3-alpha.figma.com/hub/file/1857580227/ce54020e-b061-41d5-ae60-63bbf50517cf-cover.png","description":"","url":"https://www.figma.com/community/file/1106203309697497807"}
