[{"date":"2021-10-16","duplicateCount":689,"likeCount":12,"viewCount":60915,"commentCount":0,"version":"1"},{"date":"2021-10-17","duplicateCount":689,"likeCount":12,"viewCount":60918,"commentCount":0,"version":"1"},{"date":"2021-10-18","duplicateCount":691,"likeCount":12,"viewCount":60929,"commentCount":0,"version":"1"},{"date":"2021-10-19","duplicateCount":693,"likeCount":12,"viewCount":60936,"commentCount":0,"version":"1"},{"date":"2021-10-20","duplicateCount":695,"likeCount":12,"viewCount":60946,"commentCount":0,"version":"1"},{"date":"2021-10-21","duplicateCount":697,"likeCount":12,"viewCount":60962,"commentCount":0,"version":"1"}]
