{"id":"1044511346501111119","name":"Tear of Joy • Visual Experiment","lastUpdateDate":"2021-11-22T07:15:11.188Z","publisherHandle":"fonsmans","publisherImage":"https://s3-alpha.figma.com/profile/7ebbd834-67ad-42c8-9ae2-4ed12aaac8d2","publisherId":"1216786","publisherName":"Fons Mans","thumbnailUrl":"https://s3-alpha.figma.com/hub/file/1314270172/0cdc23c8-a016-4d59-a83b-23b0d8b28233-cover.png","description":"<p>Playing around with different shading effects and blurs to create gold. Feel free to duplicate and play around with the file yourself! Want to know how I create posters like this? Subscribe to my newsletter! Receive workfiles, workflows and more <a href=\"https://www.getrevue.co/profile/fonsmans?via=twitter-card-webview\" rel=\"noreferrer noopener nofollow\" target=\"_blank\">Subscribe here</a></p>","url":"https://www.figma.com/community/file/1044511346501111119"}
