{"id":"966046489868247984","name":"Config 2021 Name Card & Agenda Builder (Community)","lastUpdateDate":"2021-04-19T18:43:51.956Z","publisherHandle":"45fe0db2_0760_4","publisherImage":"https://s3-alpha.figma.com/profile/9c6a8669-11d2-4d6d-957a-521afc930d87","publisherId":"3089906","publisherName":"Diego Ramos Retamal","thumbnailUrl":"https://s3-alpha.figma.com/hub/file/798178092/7c246091-b066-4433-872c-ec75539e8d04-cover.png","description":"<p>Diego Card</p>","url":"https://www.figma.com/community/file/966046489868247984"}
