{"id":"1014547964668359338","name":"Backend","lastUpdateDate":"2021-08-31T14:51:24.266Z","publisherHandle":"backendedutalk","publisherImage":"https://www.gravatar.com/avatar/f828c386fa9235ea7a4c9dab81ad90af?size=240&default=https%3A%2F%2Fs3-alpha.figma.com%2Fstatic%2Fuser_v_v2.png","publisherId":"1964540","publisherName":"Vũ Dương","thumbnailUrl":"https://s3-alpha.figma.com/hub/file/1092999607/88495fce-2cb9-4549-bc64-bb122670e9b5-cover.png","description":"","url":"https://www.figma.com/community/file/1014547964668359338"}
